setup.py
example/__init__.py
example/run_spider.py
example/spider_bd_tieba.py
example/spider_stock_id.py
example/tools.py
widow/__init__.py
widow/comsumer.py
widow/field.py
widow/item.py
widow/logger.py
widow/mid.py
widow/producer.py
widow/spider.py
widow/tasks.py
widow_spider.egg-info/PKG-INFO
widow_spider.egg-info/SOURCES.txt
widow_spider.egg-info/dependency_links.txt
widow_spider.egg-info/requires.txt
widow_spider.egg-info/top_level.txt