Metadata-Version: 1.1
Name: widow-spider
Version: 0.0.2
Summary: A asyncchronous,multiprocessing spider famework
Home-page: https://github.com/daijiangtian/Widow/blob/master/README.md
Author: Woe1997
Author-email: 413122031@qq.com
License: MIT
Platform: all
Classifier: Programming Language :: Python :: 3.7
Classifier: Topic :: Software Development :: Libraries
